aiopathlib-0.6.0.dist-info/METADATA
aiopathlib-0.6.0.dist-info/WHEEL
aiopathlib-0.6.0.dist-info/entry_points.txt
aiopathlib-0.6.0.dist-info/licenses/LICENSE
aiopathlib/__init__.py
aiopathlib/py.typed
aiopathlib-0.6.0.dist-info/RECORD
