Metadata-Version: 2.1
Name: aiopathlib
Version: 0.6.0
Summary: Pathlib support for asyncio
Keywords: aiopathlib,asyncpath,aiopath
Author-Email: Waket Zheng <waketzheng@gmail.com>
License: MIT
Classifier: License :: OSI Approved :: MIT License
Classifier: Development Status :: 4 - Beta
Classifier: Programming Language :: Python
Classifier: Programming Language :: Python :: 3
Classifier: Programming Language :: Python :: 3.8
Classifier: Programming Language :: Python :: 3.9
Classifier: Programming Language :: Python :: 3.10
Classifier: Programming Language :: Python :: 3.11
Classifier: Programming Language :: Python :: 3.12
Classifier: Programming Language :: Python :: 3.13
Classifier: Programming Language :: Python :: 3 :: Only
Classifier: Operating System :: POSIX
Classifier: Environment :: Web Environment
Classifier: Intended Audience :: Developers
Classifier: Topic :: Software Development
Classifier: Topic :: Software Development :: Libraries
Classifier: Framework :: AsyncIO
Project-URL: homepage, https://github.com/waketzheng/aiopathlib
Project-URL: repository, https://github.com/waketzheng/aiopathlib.git
Project-URL: Bug Tracker, https://github.com/waketzheng/aiopathlib/issues
Requires-Python: >=3.8
Requires-Dist: aiofiles>=0.8.0
